oxtables/__init__.py
oxtables/main.py
oxtables-0.0.1.dist-info/METADATA
oxtables-0.0.1.dist-info/WHEEL
oxtables-0.0.1.dist-info/top_level.txt
oxtables-0.0.1.dist-info/RECORD
