Metadata-Version: 2.1
Name: oxtables
Version: 0.0.1
Summary: A Handy Package to Draw ASCII Tables
Author: 0x68616469
Keywords: tables,th
Classifier: Development Status :: 4 - Beta
Classifier: Intended Audience :: Developers
Classifier: Programming Language :: Python :: 3
Classifier: Operating System :: Unix
Classifier: Operating System :: MacOS :: MacOS X
Classifier: Operating System :: Microsoft :: Windows
